[
  {
    "id": "IUJEZ0YxqKEuoLlzU4LR",
    "data": {
      "fact": "A single California Avocado tree can produce on average about 60 pounds or 150 fruit a year."
    }
  },
  {
    "id": "ajyXaECB1LqT0260Whpo",
    "data": {
      "fact": "It is common knowledge that most avocados can actually be almost any color! This is because they are solid and can be painted."
    }
  },
  {
    "id": "qGgvKSn29B7LbBURdpVD",
    "data": {
      "fact": "Hold my avocado.  there's now a popular avocado meme on the internet"
    }
  },
  {
    "id": "xYlxO7D9EkNTt0UHjtyB",
    "data": {
      "fact": "Bacon is an avocado"
    }
  }
]